azure_recommendations_test2/__init__.py
azure_recommendations_test2/recommendation/__init__.py
azure_recommendations_test2/recommendation/advisor_recommendations.py
azure_recommendations_test2/recommendation/network_recommendations.py
azure_recommendations_test2/recommendation/utils.py
azure_recommendations_test2/recommendation/vm_recommendations.py
azure_recommendations_test2-0.1.3.dist-info/LICENCE
azure_recommendations_test2-0.1.3.dist-info/METADATA
azure_recommendations_test2-0.1.3.dist-info/WHEEL
azure_recommendations_test2-0.1.3.dist-info/top_level.txt
azure_recommendations_test2-0.1.3.dist-info/RECORD
